{
  "id": "Otsux_Prop_Class4_Petroleum_Properties_016",
  "category": "properties_prevention",
  "subcategory": "class4_petroleum_properties",
  "title": "【問16】危険物の性質・火災予防・消火の方法：第4石油類の性状【⭐️⭐️】",

  "question": "第4石油類（潤滑油・可塑剤）に関する説明として、次のうち最も適切なものはどれか。",

  "fields": ["description"],
  "headers": [""],

  "choices": [
    { "name": "1", "description": "ギヤー油などの潤滑油は引火点が低く、常温でもガソリン並みに蒸発して可燃性蒸気を大量に発生する。"},
    { "name": "2", "description": "ギヤー油やタービン油などの潤滑油の多くは第4石油類に属し、フタル酸ジオクチルやリン酸トリクレジルのような可塑剤も第4石油類の代表例である。"},
    { "name": "3", "description": "可塑剤はすべて第2石油類（水溶性）であり、水で薄めれば危険性はほとんどなくなる。"},
    { "name": "4", "description": "第4石油類の潤滑油タンク火災では、棒状の強い注水で油面をかき回しながら冷却するのが最も有効である。"},
    { "name": "5", "description": "第4石油類は引火点が高いため、消防法上は危険物に分類されておらず、指定数量の規制も受けない。"}
  ],

  "answer": 2,

  "hint": "ヒント：第4石油類の顔ぶれは「ギヤー油・タービン油みたいな重い機械油」と「フタル酸ジオクチル(DOP)・リン酸トリクレジル(TCP)みたいな可塑剤コンビ」。背骨は『第4＝潤滑油＋可塑剤セット』って覚えておくと一発で思い出せる。",

  "explanations": [
    "選択肢1：誤り。ガソリン並みに常温でガンガン蒸発して危ないのは第1石油類側。第4石油類（潤滑油系）は引火点が高く、20℃付近では可燃性蒸気がほとんど出ないグループ。「冷えてる第4＝まずはおとなしい油」が判断軸。",
    "選択肢2：正しい。ギヤー油・タービン油・シリンダー油などの潤滑油の多くは第4石油類に属し、フタル酸ジオクチル（可塑剤）やリン酸トリクレジル（難燃性可塑剤）も第4石油類の代表例としてよく挙げられる。「第4＝潤滑油＋可塑剤セット」で丸ごと覚えると試験で拾いやすい。",
    "選択肢3：誤り。「可塑剤＝全部第2石油類」「水で薄めれば安全」というのは危険な思い込み。フタル酸ジオクチルやリン酸トリクレジルは第4石油類で、水にも溶けにくい。水でちゃぷちゃぷやっても危険性が消えるわけではない。",
    "選択肢4：誤り。第4石油類のタンク火災で棒状注水をすると、油が飛び散って延焼・二次災害のルートになる。ここは泡消火薬剤や粉末消火薬剤、CO₂などで“油面をおさえ込む”のが基本。棒状注水はNGルート。",
    "選択肢5：誤り。第4石油類も立派な消防法上の危険物で、指定数量は6,000L。『引火点が高い＝危険物じゃない』ではなく、『引火点が高いけど、大量になるとやっぱり危ないから指定数量で縛る』と整理しよう。"
  ],

  "image": null,
  "is_paid": true,
  "meta": {
    "difficulty": "basic",
    "tags": ["危険物の性質・火災予防・消火の方法", "第4石油類の性状", "潤滑油", "可塑剤", "ギヤー油", "タービン油", "フタル酸ジオクチル", "リン酸トリクレジル", "棒状注水NG", "指定数量6000L"],
    "version": "2025-12-21"
  }
}








