{
  "id": "Otsux_Prop_Special_Flammable_Properties_020",
  "category": "properties_prevention",
  "subcategory": "special_flammable_properties",
  "title": "【問20】危険物の性質・火災予防・消火の方法：特殊引火物の性状【⭐️⭐️】",

  "question": "特殊引火物の性状について、次のうち正しいものはどれか。",

  "fields": ["description"],
  "headers": [""],

  "choices": [
    { "name": "1", "description": "二硫化炭素は発火点が100℃より低く、蒸気は空気より重いため低所に滞留しやすい。" },
    { "name": "2", "description": "ジエチルエーテルは水に極めてよく溶けるため、水洗いで容易に除去できる。" },
    { "name": "3", "description": "酸化プロピレンは水と反応して分解するため、水には溶けない。" },
    { "name": "4", "description": "アセトアルデヒドは引火点が0℃以上で、常温では引火の危険が小さい。" },
    { "name": "5", "description": "二硫化炭素は比重が1より小さく、水面に浮くため拡散しにくい。" }
  ],

  "answer": 1,

  "hint": "二硫化炭素の発火点は90℃であり100℃より低い。蒸気比重は1より大きく空気より重いため低所に滞留する。液体の比重は約1.3であり水より重い。ジエチルエーテルは水にわずかにしか溶けない。酸化プロピレンは水に溶ける。アセトアルデヒドの引火点は−39℃以下である。",

  "explanations": [
    "正しい。二硫化炭素の発火点は90℃であり100℃より低く、蒸気比重は1より大きいため蒸気は低所に滞留しやすい。",
    "誤り。ジエチルエーテルは水にわずかにしか溶けないため、水洗いによる除去は適切な処理方法ではない。",
    "誤り。酸化プロピレンは水に溶ける。",
    "誤り。アセトアルデヒドの引火点は−39℃以下であり、常温でも引火の危険性がある。",
    "誤り。二硫化炭素の比重は約1.3であり水より重いため、水面に浮かない。"
  ],

  "image": null,
  "is_paid": true,
  "meta": {
    "difficulty": "basic",
    "tags": ["危険物の性質・火災予防・消火の方法", "特殊引火物の性状", "二硫化炭素", "発火点", "蒸気比重", "低所滞留", "ジエチルエーテル", "酸化プロピレン", "アセトアルデヒド"],
    "version": "2026-05-28"
  }
}



