{
  "id": "Otsux_Prop_Special_Flammable_Properties_005",
  "category": "properties_prevention",
  "subcategory": "special_flammable_properties",
  "title": "【問5】危険物の性質・火災予防・消火の方法：特殊引火物の性状",

  "question": "ジエチルエーテルの性状について、次のうち妥当でないものはどれか。",

  "fields": ["description"],
  "headers": [""],
  "choices": [
  { "name": "1", "description": "沸点が極めて低い。"},
  { "name": "2", "description": "電気の良導体であり、流動等によっても静電気が発生しにくい。"},
  { "name": "3", "description": "蒸気比重は1より大きい。"},
  { "name": "4", "description": "比重は1より小さく、水にわずかしか溶けない。"},
  { "name": "5", "description": "引火点が極めて低く、かつ、燃焼範囲も極めて広い。"}
  ],

  "answer": 2,
  "hint": "ヒント：各性状の“定数”を思い出そう：沸点≈35℃、引火点≈−45℃、燃焼範囲≈1.9〜36 vol%、液の比重≈0.7（→水より軽い）、蒸気比重≈2.6（→空気より重い）。もう一つ、電気的性質（導電性と静電気の発生しやすさ）に注意。",

  "explanations": [
    "選択肢1：妥当。沸点は約35℃で極めて低い。→ 常温でも蒸気が発生しやすく、屋内では換気・密栓が重要。",
    "選択肢2：妥当ではない。ジエチルエーテルは電気の不良導体（絶縁性）で、流動・移送・霧化時に帯電しやすい。静電火花が着火源となるため、アース・ボンディング等の帯電対策が必須。",
    "選択肢3：妥当。蒸気比重は約2.6で空気より重い。→ 低所に滞留しやすく、床面・ピット周辺で引火危険が高まる（低所排気などの設計が必要）。",
    "選択肢4：妥当。液比重は約0.7で水より軽い。水には“わずかに”溶ける一方、アルコールにはよく溶ける（可溶性の対比が重要）。",
    "選択肢5：妥当。引火点は約−45℃と極めて低く、燃焼範囲も約1.9～36 vol%と広い。→ ごく弱い着火源でも燃えやすく、濃度管理・換気が不可欠。"
  ],

  "feedback_mode": "negation",
  "image": null,
  "is_paid": true,
  "meta": {
    "difficulty": "basic",
    "tags": ["危険物の性質・火災予防・消火の方法", "特殊引火物の性状", "ジエチルエーテルの性状", "沸点", "電気不導体", "流動", "静電気", "蒸気比重", "燃焼範囲"],
    "version": "2025.8.17"
  }
}



