{
  "id": "Otsux_Law_Defined_Substances_007",
  "category": "law",
  "subcategory": "defined_substances",
  "title": "【問7】危険物に関する法令 : 消防法で規定する危険物",

  "question": "以下のうち、法別表第1に掲げる危険物の「類別」「性質」「品名」の組み合わせとして正しいものはどれか。",
  
  "fields":  ["description1","description2","description3"],
  "headers": ["類別","性質","品名"],


  "choices": [
    { "name": "1", "description1": "第1類", "description2": "酸化性固体",                 "description3": "過塩素酸塩類" },
    { "name": "2", "description1": "第3類", "description2": "可燃性固体",                 "description3": "マグネシウム" },
    { "name": "3", "description1": "第6類", "description2": "酸化性固体",                 "description3": "過酸化水素" },
    { "name": "4", "description1": "第5類", "description2": "自己反応性物質",             "description3": "ベンゼン" },
    { "name": "5", "description1": "第3類", "description2": "自然発火性物質・禁水性物質", "description3": "硫黄" }
  ],

  "answer": 1,

  "hint": "ヒント：第1類は酸化性固体、第2類は可燃性固体、第3類は自然発火性物質及び禁水性物質、第4類は引火性液体、第5類は自己反応性物質、第6類は酸化性液体。",

  "explanations": [
    "正しい。過塩素酸塩類は法別表第1において第1類（酸化性固体）に分類される品名であり、類別・性質・品名の組み合わせはすべて正しい。",
    "誤り。マグネシウムは第2類（可燃性固体）の品名である。第3類の性質は「自然発火性物質及び禁水性物質」であり、類別と性質の組み合わせが誤っている。",
    "誤り。過酸化水素は第6類に分類されるが、第6類の性質は「酸化性液体」である。「酸化性固体」は第1類の性質であり、性質の記述が誤っている。",
    "誤り。ベンゼンは第4類（引火性液体）の第1石油類に分類される。第5類（自己反応性物質）との組み合わせは誤っている。",
    "誤り。硫黄は第2類（可燃性固体）の品名である。第3類の性質は「自然発火性物質及び禁水性物質」であり、類別と性質の組み合わせが誤っている。"
  ],

  "image": null,
  "is_paid": true,
  "meta": {
    "difficulty": "basic",
    "tags": ["法令", "危険物の分類", "法別表第1", "類別対比", "第1類", "第2類", "第3類", "第4類", "第5類", "第6類"],
    "version": "2026-05-12"
  }
}