{
  "id": "Otsux_Prop_Class2_Petroleum_Properties_015",
  "category": "properties_prevention",
  "subcategory": "class2_petroleum_properties",
  "title": "【問15】危険物の性質・火災予防・消火の方法：第2石油類の性状",

  "question": "アクリル酸の性状について、次のうち妥当なものはどれか。",

  "fields": ["description"],
  "headers": [""],

  "choices": [
    { "name": "1", "description": "無臭の黄色の液体である。" },
    { "name": "2", "description": "水やエーテルには溶けない。" },
    { "name": "3", "description": "重合しやすく、重合熱が大きいので発火・爆発のおそれがある。" },
    { "name": "4", "description": "液体は素手でさわれても安全であり、蒸気も無毒である。" },
    { "name": "5", "description": "酸化性物質と混触しても、発火・爆発の恐れはない。" }
  ],

  "answer": 3,

  "hint": "ヒント：アクリル酸＝『重合暴走に要注意』の代表選手。光・熱・酸化剤・金属などがきっかけで重合が加速し、重合熱で温度が急上昇→発火・爆発リスクにつながる。一方、水やエーテルにはよく溶け、刺激臭をもつ腐食性・有害な液体だと押さえておこう。",

  "explanations": [
    "選択肢1：誤り。アクリル酸は通常“無色〜わずかに着色”の液体で、強い刺激臭（酢酸より鋭い感じ）をもつ。『黄色・無臭』という記述は性状のイメージと逆であり不適切である。",
    "選択肢2：誤り。アクリル酸は極性が高く、水やアルコール、エーテルなど多くの有機溶媒に溶ける。『水やエーテルには溶けない』という説明は、実際の溶解性と反対である。",
    "選択肢3：正しい。アクリル酸は重合しやすい物質であり、重合に伴う発熱（重合熱）が大きい。重合が暴走すると温度が急上昇し、発火・爆発に至るおそれがあるため、阻害剤の添加や低温・遮光・金属粉やさびの混入防止などの管理が重要となる。",
    "選択肢4：誤り。アクリル酸は強い腐食性をもち、皮膚・眼に触れると化学熱傷をおこす危険がある。また蒸気の吸入でも粘膜刺激や炎症を引き起こすため、『素手で触っても安全』『蒸気も無毒』という記述は危険性を過小評価している。",
    "選択肢5：誤り。過酸化物や濃硝酸などの強い酸化性物質と混触すると、急激な反応や発熱が起こり、重合や分解が進んで発火・爆発の危険がある。『酸化性物質と混触しても安全』という説明は誤りである。"
  ],

  "image": null,
  "is_paid": true,
  "meta": {
    "difficulty": "basic",
    "tags": ["危険物の性質・火災予防・消火の方法", "第2石油類の性状", "アクリル酸", "重合", "重合熱", "暴走反応", "刺激臭", "腐食性", "酸化性物質との混触危険"],
    "version": "2025-12-20"
  }
}





