{
  "id": "Otsux_Prop_Accident_Cases_And_Measures_003",
  "category": "properties_prevention",
  "subcategory": "accident_cases_and_measures",
  "title": "【問3】危険物の性質・火災予防・消火の方法：事故事例と対策",
  "question": [
    "次の文の下線部（A）～（D）のうち、事故の発生要因になると考えられるものすべてを掲げている組み合わせはどれか。",
    "「ガソリンを貯蔵していた移動タンク貯蔵所のタンクにガソリンを注入するため、（A）導電性の小さい作業服と靴を着用し、（B）タンク内を不活性ガスで置換した。タンク上部の注入口から注入管を入れ、（C）注入管の先端をタンク底部から十分に離し、（D）注入速度をできるだけ大きくしてガソリンを注入している際、タンク内から突然炎が上がった。」",
    "A. 導電性の小さい作業服と靴を着用し",
    "B. タンク内を不活性ガスで置換し",
    "C. 注入管の先端をタンク底部から十分に離し",
    "D. 注入速度をできるだけ大きくし"
  ],

  "fields": ["description"],
  "headers": [""],
  "choices": [
  { "name": "1", "description": "A、B"},
  { "name": "2", "description": "A、B、C"},
  { "name": "3", "description": "A、C、D"},
  { "name": "4", "description": "B、D"},
  { "name": "5", "description": "C、D"}
  ],

  "answer": 3,
  "hint": "ヒント：ガソリンの注入時に静電気が最大の引火要因となります。静電気は導電性の低い服装、注入管の先端が液面から離れていること、注入速度の速さで蓄積されやすいため、これらに該当する選択肢を探してみましょう。",

  "explanations": [
    "選択肢1：妥当ではありません。A（導電性の小さい作業服と靴を着用）は静電気蓄積の要因ですが、B（タンク内を不活性ガスで置換）は可燃性ガスを除去して火災リスクを低減する安全対策であり、発生要因には該当しません。",
    "選択肢2：妥当ではありません。AとCは静電気発生の要因ですが、Bの不活性ガス置換は安全対策なので組み合わせとして誤りです。",
    "選択肢3：妥当です。A（導電性の小さい作業服と靴）、C（注入管先端が液面から離れている）、D（注入速度が速い）の3つはいずれも摩擦や乱流によって静電気を発生・蓄積させやすく、引火火花の主要因となります。",
    "選択肢4：妥当ではありません。Bは安全対策、Dのみでは他の要因（A・C）を欠いているため不適切です。",
    "選択肢5：妥当ではありません。CとDは要因ですが、Aを含まないため静電気発生の全要因を網羅しておらず不完全です。"
  ],

  "image": null,
  "is_paid": true,
  "meta": {
    "difficulty": "basic",
    "tags": ["危険物の性質・火災予防・消火の方法", "事故事例と対策", "静電気蓄積", "静電気発生", "不活性ガス置換", "導電性", "可燃性ガス"],
    "version": "2025.8.6"
  }
}



