{
  "id": "Otsux_Law_Outdoor_Storage_Standards_012",
  "category": "law",
  "subcategory": "outdoor_storage_standards",

  "title": "【問12】危険物に関する法令：屋外貯蔵所の基準【⭐️⭐️⭐️】",

  "question": "屋外貯蔵所において貯蔵し、または取り扱うことが想定されている危険物の範囲に関する次の記述のうち、正しいものはどれか。",

  "fields": ["description"],
  "headers": [""],

  "choices": [
    { "name": "1", "description": "第2類では硫黄および引火性固体（引火点が0℃以上のもの）、第4類では第1石油類（引火点が0℃以上のもの）、アルコール類、第2石油類、第3石油類、第4石油類、動植物油類が屋外貯蔵所の対象となる。"},
    { "name": "2", "description": "第2類の危険物はすべて屋外貯蔵所の対象であり、第4類については第1石油類のみが対象で、アルコール類や動植物油類は含まれない。"},
    { "name": "3", "description": "第2類では硫黄のみが対象で、引火性固体は引火点にかかわらず屋外貯蔵所の対象外であるが、第4類はすべての第1〜第4石油類と動植物油類が対象となる。"},
    { "name": "4", "description": "第4類では第1〜第4石油類が対象となり、引火点の条件はなく、アルコール類や動植物油類は屋外貯蔵所では取り扱わない。"},
    { "name": "5", "description": "屋外貯蔵所は低温で危険性が高いものをまとめて扱う施設であり、引火点が0℃未満の第1石油類や第5類危険物も対象に含まれる。"}
  ],

  "answer": 1,

  "hint": "ヒント：ここは“誰を仲間に入れているか”を丸ごと覚える問題。第2類は『硫黄＋引火性固体（引火点0℃以上）だけ』で全部じゃない。第4類は『第1石油類（0℃以上）＋アルコール類＋第2〜第4石油類＋動植物油類』がフルメンバー。それ以外（第5類とか、0℃未満とか、全部の第2類…）が混ざってきたら、くさいぞ！で切り捨てる。",

  "explanations": [
    "選択肢1. 正しい。屋外貯蔵所の定義に出てくるメンバーをそのまま整理した記述であり、第2類は硫黄と一定条件の引火性固体、第4類は第1石油類（0℃以上）、アルコール類、第2〜第4石油類、動植物油類が対象となる。",
    "選択肢2. 誤り。第2類は『全部』ではなく、硫黄と一定条件の引火性固体に限定されている。また、アルコール類や動植物油類も屋外貯蔵所の対象に含まれる。",
    "選択肢3. 誤り。第2類では硫黄に加えて『引火性固体（引火点0℃以上）』も対象であり、引火性固体が一律に対象外という説明は誤りである。",
    "選択肢4. 誤り。第4類の対象は第1石油類（引火点0℃以上）であって、引火点の条件がないわけではない。また、アルコール類や動植物油類も屋外貯蔵所の対象に含まれる。",
    "選択肢5. 誤り。屋外貯蔵所の定義に第5類危険物は含まれず、第1石油類についても引火点0℃未満のものは対象外である。『低温で危険なものをまとめて扱う』という説明はイメージ先行の誤った言い換え。"
  ],

  "image": null,
  "is_paid": true,
  "meta": {
    "difficulty": "intermediate",
    "tags": ["法令", "屋外貯蔵所の基準", "対象となる危険物の範囲", "第2類", "硫黄", "引火性固体(0℃以上)", "第4類", "アルコール類", "第1〜第4石油類", "動植物油類", "出る出るポイント"],
    "version": "2025.12.25"
  }
}





