{
  "id": "Otsux_Law_Outdoor_Storage_Standards_009",
  "category": "law",
  "subcategory": "outdoor_storage_standards",

  "title": "【問9】危険物に関する法令：屋外貯蔵所の基準",
  "question":"法令上、屋外貯蔵所で貯蔵できない危険物は次のうちどれか。",

  "fields":  ["description"],
  "headers": [""],

  "choices": [
    { "name": "1", "description": "硫黄" },
    { "name": "2", "description": "アルコール類" },
    { "name": "3", "description": "自動車ガソリン" },
    { "name": "4", "description": "第1石油類（引火点0℃以上）" },
    { "name": "5", "description": "引火性固体（引火点0℃以上）" }
  ],

  "answer": 3,

  "hint": "ヒント：まずは屋外貯蔵所で仲間になる危険物の範囲を決めよう。第2類では【硫黄＋引火性固体（引火点0℃以上）】、第4類では【第1石油類（0℃以上）・アルコール類・第2〜第4石油類・動植物油類】が仲間。ここからこぼれる典型が『引火点0℃未満の第1石油類（ガソリンなど）』。この“仲間リストにちゃんと名前が載っているかどうか”を背骨にして、外れているものを1つ探そう。",

  "explanations": [
    "選択肢1. 誤り（＝貯蔵できる）。硫黄は第2類に属し、屋外貯蔵所で扱える第2類危険物として法令に挙げられているため、屋外貯蔵所で貯蔵することができる。",
    "選択肢2. 誤り（＝貯蔵できる）。アルコール類は第4類に属し、『第1石油類（0℃以上）・アルコール類・第2〜第4石油類・動植物油類』という屋外貯蔵所で扱える第4類の仲間に含まれるため、貯蔵できる。",
    "選択肢3. 正しい（＝貯蔵できない）。自動車ガソリンは第1石油類に属するが、その引火点は0℃未満であり、屋外貯蔵所で扱える第4類危険物の範囲（第1石油類のうち引火点0℃以上のもの）から外れている。そのため、屋外貯蔵所で貯蔵することはできない。",
    "選択肢4. 誤り（＝貯蔵できる）。第1石油類のうち、引火点が0℃以上のものは屋外貯蔵所で扱える第4類の一つとして法令に挙げられており、条件を満たすものは貯蔵できる。",
    "選択肢5. 誤り（＝貯蔵できる）。『引火性固体（引火点0℃以上）』は、屋外貯蔵所で扱える第2類危険物として名指しされており、この条件を満たすものは屋外貯蔵所で貯蔵できる。"
  ],

  "feedback_mode": "negation",
  "image": null,
  "is_paid": true,
  "meta": {
    "difficulty": "basic",
    "tags": ["法令", "屋外貯蔵所の基準", "第2類", "硫黄", "引火性固体(0℃以上)", "第4類", "第1石油類(0℃以上)", "自動車ガソリン(0℃未満は不可)", "貯蔵できない危険物"],
    "version": "2025-12-25"
  }
}


