{
  "id": "Otsux_Law_Alarm_Systems_001",
  "category": "law",
  "subcategory": "alarm_systems",

  "title": "【問1】法令：警報設備",
  "question": [
    "法令上、警報設備の設置義務について、次の文の（）に当てはまる数値は、次のうちどれか。",
    "指定数量の倍数が（）以上の危険物を取り扱う製造所等（移動タンク貯蔵所を除く）では、警報設備の設置が義務付けられている。"
  ],

  "fields":  ["description"],
  "headers": [""],

  "choices": [
    { "name": "1", "description": "5"},
    { "name": "2", "description": "10"},
    { "name": "3", "description": "20"},
    { "name": "4", "description": "30"},
    { "name": "5", "description": "50"}
  ],

  "answer": 2,
  "hint": "ヒント：「指定数量の“倍数”が10以上 →（移動タンク除外で）警報“設備”が要る」。10％（=0.1倍）や1/10と取り違えない。",

  "explanations": [
    "1. 誤り：5では基準に達しない。設置義務のトリガーは“倍数10以上”。",
    "2. 正しい：指定数量の“倍数が10以上”となる製造所等（移動タンク貯蔵所を除く）は、警報設備の設置義務がある。",
    "3. 誤り：20は正しい基準（10）より厳しすぎるダミー。10以上で義務が発生する。",
    "4. 誤り：30も同様に過大なダミー。基準は10以上。",
    "5. 誤り：50も過大なダミー。数値の“向き”を問うひっかけに注意。"
  ],

  "image": null,
  "is_paid": true,
  "meta": {
    "difficulty": "basic",
    "tags": ["法令", "警報設備", "設置義務", "製造所等", "移動タンク貯蔵所", "10以上", "指定数量", "倍数", "自動火災報知"],
    "version": "2025-10-14"
  }
}

