{
  "id": "Otsux_Law_Firefighting_Equipment_Standards_014",
  "category": "law",
  "subcategory": "firefighting_equipment_standards",

  "title": "【問14】法令：消火設備と設置基準",


  "question": "法令上、第5種の消火設備のみを設ければよい製造所等は、次のうちどれか。",

  "fields":  ["description"],
  "headers": [""],


  "choices": [
    { "name": "1", "description": "指定数量の倍数が10の灯油を取り扱う一般取扱所" },
    { "name": "2", "description": "指定数量の倍数が20のエタノールを販売する第二種販売取扱所" },
    { "name": "3", "description": "指定数量の倍数が100の軽油を貯蔵する屋外貯蔵所" },
    { "name": "4", "description": "指定数量の倍数が150のガソリンを貯蔵する地下タンク貯蔵所" },
    { "name": "5", "description": "指定数量の倍数が400の重油を移送する移送取扱所" }
  ],


  "answer": 4,
  "hint": "ヒント：『地下タンク＝第5種のみ×2個』。それ以外（一般取扱所／第二種販売取扱所／屋外貯蔵所／移送取扱所）は、規模・品名・数量などの条件により第1〜第3・第4種が絡むため「第5種のみ」にはならない。",


  "explanations": [
    "1. 誤り：一般取扱所は作業内容・数量・品名等により他種（第1〜第3・第4）が必要となる場合があり、第5種のみでは足りない。",
    "2. 誤り：第二種販売取扱所も構造・取扱量等により他種が求められ得るため、第5種のみでは足りない。",
    "3. 誤り：屋外貯蔵所は可燃性液体の対策で第3種（泡・水噴霧等）が想定されやすく、第5種のみでは足りない。",
    "4. 正しい：地下タンク貯蔵所は第5種の消火設備を2個以上設ければよい（他種の要求なし）。",
    "5. 誤り：移送取扱所は配管・ポンプ等の条件によって他種設備が必要となり得るため、第5種のみでは足りない。"
  ],


  "image": null,
  "is_paid": true,
  "meta": {
    "difficulty": "basic",
    "tags": ["法令", "消火設備と設置基準", "第5種", "一般取扱所", "第二種販売取扱所", "屋外貯蔵所", "地下タンク貯蔵所", "移送取扱所", "第5種×2個"],
    "version": "2025-10-14"
  }
}


