{
  "id": "Otsux_Law_Temporary_Storage_Handling_003",
  "category": "law",
  "subcategory": "temporary_storage_handling",
  "title": "【問3】法令：仮貯蔵と仮取扱い",
  "question": "法令上、指定数量以上の危険物を製造所等以外の場所で仮に貯蔵し、又は取り扱う場合について、次のうち正しいものはどれか。",

  "fields":  ["description"],
  "headers": [""],
  "choices": [
    { "name": "1", "description": "市町村長等に届け出れば、危険物を貯蔵し、又は取り扱うことができる。"},
    { "name": "2", "description": "危険物を貯蔵し、又は取り扱う場合には、危険物保安監督者の選任が必要である。"},
    { "name": "3", "description": "危険物を貯蔵し、又は取り扱うことができる期間に制限はない。"},
    { "name": "4", "description": "貯蔵し、または取り扱うことのできる危険物の指定数量の倍数は10以下である。"},
    { "name": "5", "description": "所轄消防長又は消防署長の承認を受けないで指定数量以上の危険物を貯蔵し、又は取り扱っている者は、危険物の除去を命じられることがある。"}
  ],

  "answer": 5,
  "hint": "ヒント： 仮貯蔵・仮取扱いを承認なしに行った場合の法令上の措置に注目し、“除去を命じる”というキーワードを条文で探してみましょう。",

  "explanations": [
    "【選択肢1】誤りです。市町村長等への届け出ではなく、所轄消防長または消防署長の<strong>承認</strong>が必要です。仮貯蔵・仮取扱いは消防法第13条の2に基づく手続きであり、届け出のみでは行えません。<br>",
    "【選択肢2】誤りです。危険物保安監督者の選任は通常の貯蔵・取扱いに必要ですが、仮貯蔵・仮取扱いの場合は所轄消防長または消防署長の承認を受けることが要件であり、保安監督者の選任は不要です。<br>",
    "【選択肢3】誤りです。仮貯蔵・仮取扱いには<strong>期間の制限（10日以内）</strong>があり、無制限に行えるという規定はありません。<br>",
    "【選択肢4】誤りです。数量の倍数制限を設ける条文は存在せず、指定数量以上の危険物を仮に貯蔵・取扱う際の要件は承認と期間の制限のみです。<br>",
    "【選択肢5】正しいです。製造所等以外の場所で指定数量以上の危険物を仮貯蔵・取扱うには、所轄消防長または消防署長の承認が必須です。承認なしに行った場合、消防長等は危険物の除去や必要な措置を命ずることができます（消防法第13条の2第4項）。<br>"
  ],

  "image": null,
  "is_paid": true,
  "meta": {
    "difficulty": "basic",
    "tags": [
      "法令",
      "仮貯蔵",
      "仮取扱い",
      "指定数量以上の危険物",
      "貯蔵所",
      "取扱所",
      "所轄消防長",
      "消防署長",
      "政令",
      "消防法第13条の2第4項"
    ],
    "version": "2025.7.28"
  }
}