{
  "id": "Otsux_Law_Preventive_Regulation_Items_007",
  "category": "law",

  "subcategory": "preventive_regulation_items",

  "title": "【問7】危険物に関する法令：予防規程に定めるべき事項",

  "question": "法令上、営業用給油取扱所の予防規程に定めなければならない事項に該当しないものはどれか。",

  "fields": ["description"],
  "headers": [""],

  "choices": [
    { "name": "1", "description": "危険物の保安に係る作業に従事する者に対する保安教育に関すること。" },
    { "name": "2", "description": "危険物保安監督者がその職務を行うことができない場合にその職務を代行する者に関すること。" },
    { "name": "3", "description": "危険物の保安に関する記録に関すること。" },
    { "name": "4", "description": "製造所等の位置、構造および設備を明示した書類および図面の整備に関すること。" },
    { "name": "5", "description": "火災保険・損害保険の契約条件および保険金請求の方法に関すること。" }
  ],

  "answer": 5,

  "hint": "予防規程は危険物施設における自主保安の規程であり、人員体制・教育・記録・図面整備はいずれも保安の維持・確認に直結する事項である。保険契約や保険金請求は火災後の事後処理であり、この目的の範囲外である。",

  "explanations": [
    "正しい。危険物の保安に係る作業に従事する者に対する保安教育（計画・実施・記録等）は、保安水準の維持・向上を図るため予防規程に定めるべき事項である。",
    "正しい。危険物保安監督者が旅行・疾病その他の事故によりその職務を行うことができない場合に職務を代行する者は、保安体制の継続性を確保するため予防規程に定めるべき事項である。",
    "正しい。危険物の保安に関する記録は、保安活動の実施状況を確認・管理するため予防規程に定めるべき事項である。",
    "正しい。製造所等の位置・構造・設備を明示した書類および図面の整備は、施設の保安管理の基礎となるため予防規程に定めるべき事項である。",
    "誤り。保険の契約条件や保険金請求は火災後の損害処理に関する営業上の事項であり、火災予防のための自主保安規程である予防規程の必須記載事項には当たらない。"
  ],

  "feedback_mode": "negation",
  "image": null,
  "is_paid": true,
  "meta": {
    "difficulty": "basic",
    "tags": ["法令", "予防規程に定めるべき事項", "保安教育", "保安監督者代行", "保安記録", "図面整備"]
  }
}