{
  "id": "Otsux_Law_Preventive_Regulation_Items_005",
  "category": "law",

  "subcategory": "preventive_regulation_items",

  "title": "【問5】危険物に関する法令：予防規程に定めるべき事項",

  "question": "営業用給油取扱所の予防規程に関する次の記述のうち、誤っているものはどれか。",

  "fields":  ["description"],
  "headers": [""],

  "choices": [
    { "name": "1", "description": "予防規程は所有者等が定め、市町村長等の認可を受ける。" },
    { "name": "2", "description": "セルフ方式では、顧客に対する監視その他保安のための措置を予防規程に定める。" },
    { "name": "3", "description": "予防規程は所有者および従業員が遵守すべきものであり、顧客も法的な遵守義務者に含まれる。" },
    { "name": "4", "description": "予防規程の内容を変更する場合、市町村長等の認可を受ける必要がある。" },
    { "name": "5", "description": "市町村長等は、予防規程違反があるとき、必要な措置や使用停止を命ずることがある。" }
  ],

  "answer": 3,
  "hint": "ヒント：ここ要チェック！“誰が守る？”で差がつく。→ 所有者＋従業員はセット。じゃあ顧客は…？ それとセルフなら“監視・保安措置”の明記は鉄板、思い出して！",

  "explanations": [
    "選択肢1. 正しい。予防規程の作成主体は所有者等であり、市町村長等の認可を受けて初めて効力を生ずる。",
    "選択肢2. 正しい。セルフ方式では、顧客に対する監視・保安措置（監視体制、非常停止、禁止事項の掲示、異常時対応等）を規定する必要がある。",
    "選択肢3. 誤り（正解）。遵守義務は所有者および従業員に課される。顧客は法令上の“遵守義務者”には含まれない（顧客には掲示・指示の遵守を求める運用はあるが、予防規程の直接の遵守義務者ではない）。",
    "選択肢4. 正しい。認可後に内容を変更する場合も、原則として所定の手続（変更認可）が必要。",
    "選択肢5. 正しい。市町村長等は、予防規程違反など火災予防上支障がある場合に、必要な措置命令や使用停止命令を発することができる。"
  ],

  "feedback_mode": "negation",
  "image": null,
  "is_paid": true,
  "meta": {
    "difficulty": "basic",
    "tags": ["法令", "予防規程", "作成主体", "認可", "遵守義務", "セルフスタンド", "措置命令", "使用停止命令"],
    "version": "2025-11-25"
  }
}