{
  "id": "Otsux_Law_Designated_Quantities_005",
  "category": "law",

  "subcategory": "designated_quantities",
  "title": "【問5】危険物に関する法令：危険物の指定数量 【⭐️】" ,

  "question": [
    "法令上、次の危険物を同一場所で貯蔵する場合、指定数量の倍数以上となる組み合わせは次のうちどれか。"
  ],

  "fields": ["description1", "description2"],
  "headers": ["", ""],

  "choices": [
  { "name": "1", "description1": "ガソリン   100L", "description2": "灯油     400L" },
  { "name": "2", "description1": "灯油      500L", "description2": "軽油       400L" },
  { "name": "3", "description1": "軽油      400L", "description2": "重油      1,000L" },
  { "name": "4", "description1": "メタノール  200L", "description2": "ガソリン    100L" },
  { "name": "5", "description1": "エタノール    200L", "description2": "灯油     400L" }
  ],

  "answer": 4,

  "hint": "ヒント：各品名の指定数量：ガソリン（第1石油類・非水溶性）200L、灯油・軽油（第2石油類・非水溶性）各1,000L、重油（第3石油類・非水溶性）2,000L、メタノール・エタノール（アルコール類）各400L。指定数量の倍数は、各危険物の貯蔵量を指定数量で割った値の合計で求める。合計が1.0以上となる組み合わせを選ぶ。",

  "explanations": [
    "誤り。ガソリン100Lの倍数は100÷200＝0.5倍、灯油400Lの倍数は400÷1,000＝0.4倍で、合計0.9倍となり1.0未満である。",
    "誤り。灯油500Lの倍数は500÷1,000＝0.5倍、軽油400Lの倍数は400÷1,000＝0.4倍で、合計0.9倍となり1.0未満である。",
    "誤り。軽油400Lの倍数は400÷1,000＝0.4倍、重油1,000Lの倍数は1,000÷2,000＝0.5倍で、合計0.9倍となり1.0未満である。",
    "正しい。メタノール200Lの倍数は200÷400＝0.5倍、ガソリン100Lの倍数は100÷200＝0.5倍で、合計1.0倍となり指定数量の倍数以上に該当する。",
    "誤り。エタノール200Lの倍数は200÷400＝0.5倍、灯油400Lの倍数は400÷1,000＝0.4倍で、合計0.9倍となり1.0未満である。"
  ],

  "image": null,
  "is_paid": true,

    "meta": {
    "difficulty": "basic",
    "tags": ["法令", "危険物の指定数量", "第4類危険物", "計算問題", "指定数量の合算", "過去問パターン"],
    "version": "2026-05-13"
  }
}




