{
  "id": "Otsux_Law_Designated_Quantities_006",
  "category": "law",
  "subcategory": "designated_quantities",
  "title": "【問6】法令：危険物の指定数量" ,
  "question": [
    "屋内貯蔵所に灯油2,000Lと軽油4,000Lを貯蔵している。これらと同時に貯蔵するとき、次のうち指定数量の倍数が10となるのはどれか。"
  ],
  "fields": ["class", "property"],
  "headers": ["", ""],
  "choices": [
  { "name": "1", "class": "ガソリン", "property": "1,000L" },
  { "name": "2", "class": "二硫化炭素", "property": "300L" },
  { "name": "3", "class": "ベンゼン", "property": "1,200L" },
  { "name": "4", "class": "アセトン", "property": "800L" },
  { "name": "5", "class": "エタノール", "property": "1,600L" }
  ],
  "answer": 5,
  "hint": "ヒント：灯油と軽油はどちらも「第2石油類（非水溶性）」に分類されます。→ 同じ類なので貯蔵量を合算してから倍数を計算します。(2,000L+4,000L)÷1,000L=6倍。 つまり、すでに「6倍」分の危険物が貯蔵されている状態です。",
  "explanations": [
    " ガソリンは「第1石油類（非水溶性）」に分類され指定数量は 200L です。(1,000L ÷ 200L) = 5 👉 つまり、6倍 + 5倍 = 11倍です。<br>",
    " 二硫化炭素は「特殊引火物」に分類され指定数量は50Lです。(300L ÷ 50L) = 6 👉 つまり、6倍 + 6倍 = 12倍です。<br>",
    " ベンゼンは「第1石油類（非水溶性）」に分類され指定数量は 200L です。(1,200L ÷ 200L) = 6 👉 合計すると、6倍 + 6倍 = 12倍です。<br>",
    " アセトンは「第1石油類（水溶性）」に分類され指定数量は 400L です。(800L ÷ 400L) = 2 👉 合計すると、6倍 + 2倍 = 8倍です。<br>",
    " エタノールは「アルコール類」に分類され指定数量は 400L です。 (1,600L ÷ 400L) = = 4 👉 6倍 + 4倍 = 10倍になります。👉 よって、この選択肢が正解です。<br>"
  ],
  "image": null,
  "is_paid": true,
  "meta": {
    "difficulty": "basic",
    "tags": ["法令", "危険物の指定数量", "技術基準", "火災予防条例", "指定数量の倍数", "計算問題", "分類と指定数量"],
    "version": "2025.7.17"
  }
}



