{
  "id": "Otsux_Law_Designated_Quantities_013",
  "category": "law",

  "subcategory": "designated_quantities",
  "title": "【問13】危険物に関する法令：危険物の指定数量 【⭐️】" ,

  "question": [
  "法令上、危険物を同一場所で貯蔵する場合について、「アルコール水溶液が危険物として指定数量の倍数計算に算入され、なおかつ全体の指定数量の倍数が1.0未満にとどまる組合せ」として最も適切なものはどれか。"
],

  "fields": ["description1", "description2"],
  "headers": ["", ""],

  "choices": [
    { "name": "1", "description1": "ガソリン   120L",              "description2": "灯油     600L" },
    { "name": "2", "description1": "アセトン   200L",              "description2": "重油     800L" },
    { "name": "3", "description1": "エタノール水溶液 240L(60％)", "description2": "軽油     300L" },
    { "name": "4", "description1": "二硫化炭素   20L",             "description2": "ガソリン   100L" },
    { "name": "5", "description1": "メタノール水溶液 350L(55％)", "description2": "重油     800L" }
  ],

  "answer": 3,

  "hint": "ヒント：アルコール水溶液はアルコール分（重量）が60％以上のものが危険物（アルコール類、指定数量400L）として倍数計算に算入され、60％未満のものは危険物に該当せず除外される。設問の条件は、アルコール水溶液が算入される組み合わせであること、かつ合計倍数が1.0未満であること、の2点を同時に満たす必要がある。",

  "explanations": [
    "誤り。この組合せにはアルコール水溶液が含まれておらず、設問の条件を満たさない。なお倍数は120÷200＋600÷1,000＝0.6＋0.6＝1.2倍で1.0以上となる。",
    "誤り。この組合せにはアルコール水溶液が含まれておらず、設問の条件を満たさない。なお倍数は200÷400＋800÷2,000＝0.5＋0.4＝0.9倍である。",
    "正しい。エタノール水溶液240L（60％）はアルコール分60％のためアルコール類として危険物に該当し、指定数量400Lで算入される。倍数は240÷400＋300÷1,000＝0.6＋0.3＝0.9倍で1.0未満となり、設問の2条件をともに満たす。",
    "誤り。この組合せにはアルコール水溶液が含まれておらず、設問の条件を満たさない。なお倍数は20÷50＋100÷200＝0.4＋0.5＝0.9倍である。",
    "誤り。メタノール水溶液350L（55％）はアルコール分（重量）60％未満のため危険物に該当せず、倍数計算から除外される。設問の条件（アルコール水溶液を算入する）を満たさない。"
  ],

  "image": null,
  "is_paid": true,

  "meta": {
    "difficulty": "basic",
    "tags": [ "法令", "指定数量の倍数", "第4類危険物", "計算問題", "アルコール水溶液", "アルコール類の60％境界"],
    "version": "2026-05-13"
  }
}




