{
  "id": "Otsux_Law_Safety_Distance_009",
  "category": "law",
  "subcategory": "safety_distance",

  "title": "【問9】危険物に関する法令：保安距離",
  "question": "次の記述のうち、法令に適合していないものはどれか。ただし、当該建築物等との間に防火上有効な塀はないものとし、特例基準が適用されるものを除く。",

  "fields":  ["description"],
  "headers": [""],

  "choices": [
    { "name": "1", "description": "重要文化財として指定された建造物：50m以上" },
    { "name": "2", "description": "特別高圧架空電線（使用電圧が34.5kV〈34,500V〉）：水平距離3m以上" },
    { "name": "3", "description": "製造所等の敷地外にある住居：10m以上" },
    { "name": "4", "description": "大学：30m以上" },
    { "name": "5", "description": "高圧ガス保安法により都道府県知事の許可を受けた貯蔵所：20m以上" }
  ],

  "answer": 4,


  "hint": "ヒント：保安距離の対象になる「学校」は幼稚園（保育所含む）〜高校まで。大学・短大は含まれない。距離の基準もセットで確認：住居10m、学校・病院・劇場30m、重要文化財の建造物50m、高圧ガス施設20m、電線は7,000V超〜35,000V以下で3m、35,000V超で5m。",

  "explanations": [
    "正しい。危険物の規制に関する政令第9条第1項第1号ハにより、文化財保護法の規定により重要文化財に指定された建造物に対する保安距離は50m以上と定められている。本選択肢は基準どおりであり、法令に適合する。",
    "正しい。同政令第9条第1項第1号ホにより、使用電圧が7,000Vを超え35,000V以下の特別高圧架空電線に対する保安距離は水平距離3m以上である。34,500Vはこの範囲に該当し、本選択肢は法令に適合する。",
    "正しい。同政令第9条第1項第1号により、製造所等の存する敷地外にある住居に対する保安距離は10m以上と定められている。本選択肢は基準どおりであり、法令に適合する。",
    "誤り。同政令第9条第1項第1号ロにおける「学校」とは、学校教育法第1条に規定する幼稚園、小学校、中学校、義務教育学校、高等学校、中等教育学校、特別支援学校を指す。大学は同条に規定されるが、保安距離の対象となる施設としては政令上列挙されておらず、対象外である。したがって大学に対する保安距離の規定は存在せず、本選択肢の記述は法令に適合しない。",
    "正しい。同政令第9条第1項第1号ニにより、高圧ガス保安法の適用を受ける貯蔵所に対する保安距離は20m以上と定められている。本選択肢は基準どおりであり、法令に適合する。"
  ],

  "feedback_mode": "negation",
  "image": null,
  "is_paid": true,
  "meta": {
    "difficulty": "intermediate",
    "tags": ["法令", "保安距離", "学校の範囲", "特別高圧架空電線", "重要文化財の建造物", "高圧ガス", "境界値"],
    "version": "2026-04-04"
  }
}