{
  "id": "Otsux_Law_License_Issuance_005",
  "category": "law",

  "subcategory": "license_issuance",
  "title": "【問5】危険物に関する法令：免状の交付・書換え・再交付",

  "question": "法令上、危険物取扱者の免状に関する記述について、次のうち正しいものはどれか。",

  "fields":  ["description"],
  "headers": [""],

  "choices": [
    { "name": "1", "description": "危険物取扱者が消防法又は消防法に基づく命令の規定に違反しているときは、所轄消防署長から免状の返納を命ぜられることがある。" },
    { "name": "2", "description": "免状を汚損したとき、再交付の申請をすることができる。" },
    { "name": "3", "description": "居住地を変更したとき、免状の書換えをしなければならない。" },
    { "name": "4", "description": "免状の返納を命じられた者は、その日から起算して2年を経過しないと免状の交付を受けることができない。" },
    { "name": "5", "description": "再交付は、居住地又は勤務地を管轄する都道府県知事に申請しなければならない。" }
  ],

  "answer": 2,
  "hint": "ヒント：再交付の申請ができるのは、「亡失・滅失・〇〇・破損」の4つ。〇〇に入るのは？",

  "explanations": [
    "誤り。免状の返納命令権限は都道府県知事であり、消防署長ではない。",
    "正しい。免状の再交付事由は「亡失・滅失・汚損・破損」の4つであり、汚損はこれに該当する。",
    "誤り。住所は免状の記載事項ではないため、住所の変更は書換えの対象ではない。",
    "誤り。返納命令等により交付制限がかかる期間は1年であり、2年ではない。",
    "誤り。再交付の申請先は免状を交付または書換えした都道府県知事であり、居住地や勤務地の知事ではない。"
  ],

  "image": null,
  "is_paid": true,
  "meta": {
    "difficulty": "basic",
    "tags": ["法令", "免状の交付・書換え・再交付", "汚損", "返納命令", "再交付の申請先", "住所は記載事項に非該当", "待ち期間1年"],
    "version": "2026-04-10"
  }
}


