{
  "id": "Otsux_Law_Simple_Tank_Storage_Standards_022",
  "category": "law",
  "subcategory": "simple_tank_storage_standards",

  "title": "【問22】危険物に関する法令：簡易タンク貯蔵所の基準",

  "question": "次のうち、簡易タンク貯蔵所の基準として“すべて”適合しているものはどれか。",

  "fields": ["description"],

  "headers": [""],

  "choices": [
    { "name": "1", "description": "屋外はタンク周囲に幅1m以上の保有空地、屋内は床不浸透＋みぞ／囲いで室外流出を防止。設置は600L×最大3基で、同一品名の複数設置は不可。タンクは確実固定・外面さび止め、通気は無弁通気管、標識・防火掲示は見やすい箇所に設ける。" },
    { "name": "2", "description": "屋外の保有空地は0.5m以上で足り、屋内は床不浸透なら室外放流でも可。設置は600L×最大3基、同一品名の複数可。通気は臭気対策のため止め弁付きでもよい。" },
    { "name": "3", "description": "屋外1m空地は確保するが、標識・掲示は任意。通気は無弁でも弁付きでも可。設置数は固定・防錆等が整えば上限なし。" },
    { "name": "4", "description": "屋内は床不浸透＋みぞで集め、緊急時は排水管で屋外側溝へ放流。設置は600L×最大4基、同一品名は2基まで可。通気は無弁。" },
    { "name": "5", "description": "屋外1m空地・確実固定・さび止めは行うが、通気は地下タンク同様に先端を地上4m以上とする。標識・掲示は省略可。" }
  ],

  "answer": 1,

  "hint": "ヒント：一緒に要点を“指差し確認”！屋外＝**1m空地**、屋内＝**不浸透＋みぞ/囲いで室外NG**、設置＝**600L×最大3基**＆**同一品名×**、通気＝**無弁**、さらに**確実固定＋さび止め＋標識/掲示**。ぜーんぶ揃ってるのはどれ？",

  "explanations": [
    "1. 正しい（正解）。簡易タンクの主要要件を過不足なく満たす“フルセット”。",
    "2. 誤り。保有空地は1m以上、屋内からの室外放流は不可、同一品名は複数不可、通気は無弁で閉止不可。",
    "3. 誤り。標識・掲示は必置、通気の弁付きは不可、設置数は上限3基で“上限なし”にはならない。",
    "4. 誤り。室外放流は不可、設置は最大3基、同一品名は複数不可。",
    "5. 誤り。通気先端4mは地下タンクの要件で簡易タンクには不要。標識・掲示は省略不可。"
  ],

  "image": null,
  "is_paid": true,
  "meta": {
    "difficulty": "advanced",
    "tags": ["法令", "簡易タンク貯蔵所の基準", "保有空地1m", "屋内 不浸透床", "みぞ・囲い", "600L×3基", "同一品名不可", "無弁通気管", "確実固定", "防錆塗装", "標識・掲示", "出る出る", "シナリオ適合"],
    "version": "2025-10-30"
  }
}

