{
  "id": "Otsux_Law_Safety_Supervisors_002",
  "category": "law",

  "subcategory": "safety_supervisors",
  "title": "【問2】危険物に関する法令：危険物保安監督者【⭐️⭐️】",

  "question": "法令上、危険物保安監督者に関する説明として、次のうち誤っているものはどれか。",

  "fields":  ["description"],
  "headers": [""],
  
  "choices": [
    { "name": "1", "description": "危険物保安監督者は危険物の取扱作業の実施に際し、当該作業が法令の基準及び予防規程等の保安に関する規定に適合するように作業者に対し、必要な指示を与えなければならない。" },
    { "name": "2", "description": "危険物保安監督者は、危険物の取扱作業に関して保安の監督をする場合は、誠実にその職務を行わなければならない。" },
    { "name": "3", "description": "製造所等において、危険物取扱者以外の者は、危険物保安監督者が立ち会わなければ、危険物を取り扱うことができない。" },
    { "name": "4", "description": "危険物施設保安員を置かなくてもよい製造所等の危険物保安監督者は、規則で定める危険物施設保安員の業務を行わなければならない。" },
    { "name": "5", "description": "選任の要件である6か月以上の実務経験は、製造所等における実務経験に限定されるものである。" }
  ],

  "answer": 3,
  "hint": "ヒント：無資格者に立ち会うことができるのは、甲種と乙種の危険物取扱者のみ。では「危険物保安監督者」の役割は何だろう？",

  "explanations":  [
    "正しい。危険物保安監督者は、危険物の取扱作業の実施に際し、技術上の基準及び予防規程等の保安に関する規定に適合するよう、作業者に対して必要な指示を与えなければならない（危険物の規制に関する規則第48条第1項）。",
    "正しい。危険物保安監督者は、危険物の取扱作業に関して保安の監督をするときは、誠実にその職務を行わなければならない（消防法第13条第1項）。",
    "誤り。危険物取扱者以外の者が危険物を取り扱う場合に立ち会うのは甲種又は乙種の危険物取扱者であり（消防法第13条第3項）、危険物保安監督者ではない。立会いの役割と保安監督の役割は別である。",
    "正しい。危険物施設保安員を置かない製造所等では、危険物保安監督者が規則で定める危険物施設保安員の業務を行わなければならない（危険物の規制に関する規則第48条第2項）。",
    "正しい。選任要件である6か月以上の実務経験は、製造所等における危険物取扱いの実務経験に限られる（消防法第13条第1項）。"
  ],

  "feedback_mode": "negation",
  "image": null,
  "is_paid": true,

  "meta": {
    "difficulty": "intermediate",
    "tags": ["法令", "危険物保安監督者", "危険物施設保安員", "技術上の基準", "立会い", "甲種・乙種", "予防規程", "実務6か月"],
    "version": "2026-04-13"
  }
}